openload/__init__.py
openload/api_exceptions.py
openload/openload.py
pyopenload-0.7.dist-info/LICENSE.txt
pyopenload-0.7.dist-info/METADATA
pyopenload-0.7.dist-info/WHEEL
pyopenload-0.7.dist-info/top_level.txt
pyopenload-0.7.dist-info/RECORD
