Metadata-Version: 2.1
Name: pyopenload
Version: 0.7
Summary: Python wrapper for openload.co API
Home-page: https://github.com/mohan3d/PyOpenload
Author: Mohaned Magdy
Author-email: mohan3d94@gmail.com
License: MIT
Keywords: openload,wrapper,api,api client
Platform: UNKNOWN
Classifier: Development Status :: 4 - Beta
Classifier: Intended Audience :: Developers
Classifier: Topic :: Internet :: WWW/HTTP
Classifier: License :: OSI Approved :: MIT License
Classifier: Programming Language :: Python :: 2
Classifier: Programming Language :: Python :: 2.7
Classifier: Programming Language :: Python :: 3
Classifier: Programming Language :: Python :: 3.3
Classifier: Programming Language :: Python :: 3.4
Classifier: Programming Language :: Python :: 3.5
Classifier: Programming Language :: Python :: 3.6
Classifier: Programming Language :: Python :: 3.7
Requires-Dist: requests (>=2.20.0)
Requires-Dist: requests-toolbelt (==0.9.1)
